rrl.py
rrl-0.3.1.dist-info/LICENSE
rrl-0.3.1.dist-info/WHEEL
rrl-0.3.1.dist-info/METADATA
rrl-0.3.1.dist-info/RECORD
